{
  "info": {
    "name": "璃月10-绝云间-2",
    "type": "collect",
    "author": "寒烟",
    "version": "1.1",
    "description": "路边有小宝",
    "map_name": "Teyvat",
    "bgi_version": "0.45.0"
  },
  "positions": [
    {
      "id": 1,
      "x": 1045.53,
      "y": 950.63,
      "type": "teleport",
      "move_mode": "walk",
      "action": "",
      "action_params": ""
    },
    {
      "id": 2,
      "x": 991.34,
      "y": 904.49,
      "type": "path",
      "move_mode": "fly",
      "action": "",
      "action_params": ""
    },
    {
      "id": 3,
      "x": 980.52,
      "y": 850.56,
      "type": "path",
      "move_mode": "dash",
      "action": "",
      "action_params": ""
    },
    {
      "id": 4,
      "x": 956.01,
      "y": 776.45,
      "type": "path",
      "move_mode": "dash",
      "action": "",
      "action_params": ""
    },
    {
      "id": 5,
      "x": 892.5,
      "y": 748.02,
      "type": "path",
      "move_mode": "dash",
      "action": "",
      "action_params": ""
    }
  ]
}