{
  "info": {
    "name": "璃月9-南天门东-3-1",
    "type": "collect",
    "author": "寒烟",
    "version": "1.1",
    "description": "",
    "map_name": "Teyvat",
    "bgi_version": "0.45.0"
  },
  "positions": [
    {
      "id": 1,
      "x": 1389.02,
      "y": 516.48,
      "action": "",
      "move_mode": "walk",
      "action_params": "",
      "type": "teleport"
    },
    {
      "id": 2,
      "x": 1376.46,
      "y": 491.83,
      "action": "",
      "move_mode": "dash",
      "action_params": "",
      "type": "path"
    },
    {
      "id": 3,
      "x": 1476.63,
      "y": 485.62,
      "action": "",
      "move_mode": "dash",
      "action_params": "",
      "type": "path"
    },
    {
      "id": 4,
      "x": 1561.48,
      "y": 483.03,
      "action": "stop_flying",
      "move_mode": "fly",
      "action_params": "200",
      "type": "path"
    }
  ]
}